datetimejson/__init__.py
datetimejson/py.typed
datetimejson-0.1.8.dist-info/LICENSE
datetimejson-0.1.8.dist-info/METADATA
datetimejson-0.1.8.dist-info/WHEEL
datetimejson-0.1.8.dist-info/top_level.txt
datetimejson-0.1.8.dist-info/RECORD
