Metadata-Version: 2.2
Name: datetimejson
Version: 0.1.8
Summary: Read and write json files with datetime objects
Author-email: Matthieu Boileau <matthieu.boileau@math.unistra.fr>
License: MIT
Project-URL: Homepage, https://github.com/boileaum/datetimejson
Classifier: Programming Language :: Python :: 3
Classifier: License :: OSI Approved :: MIT License
Classifier: Operating System :: OS Independent
Requires-Python: >=3.6
License-File: LICENSE
